{
  "Realizar login-0" : {
    "transaction" : "Realizar login-0",
    "sampleCount" : 1,
    "errorCount" : 0,
    "errorPct" : 0.0,
    "meanResTime" : 305.0,
    "medianResTime" : 305.0,
    "minResTime" : 305.0,
    "maxResTime" : 305.0,
    "pct1ResTime" : 305.0,
    "pct2ResTime" : 305.0,
    "pct3ResTime" : 305.0,
    "throughput" : 3.278688524590164,
    "receivedKBytesPerSec" : 2.4398053278688523,
    "sentKBytesPerSec" : 2.8624487704918034
  },
  "Realizar login-1" : {
    "transaction" : "Realizar login-1",
    "sampleCount" : 1,
    "errorCount" : 0,
    "errorPct" : 0.0,
    "meanResTime" : 323.0,
    "medianResTime" : 323.0,
    "minResTime" : 323.0,
    "maxResTime" : 323.0,
    "pct1ResTime" : 323.0,
    "pct2ResTime" : 323.0,
    "pct3ResTime" : 323.0,
    "throughput" : 3.0959752321981426,
    "receivedKBytesPerSec" : 18.119315982972136,
    "sentKBytesPerSec" : 2.231279024767802
  },
  "Excluir usuários" : {
    "transaction" : "Excluir usuários",
    "sampleCount" : 100,
    "errorCount" : 50,
    "errorPct" : 50.0,
    "meanResTime" : 3.3800000000000012,
    "medianResTime" : 2.0,
    "minResTime" : 1.0,
    "maxResTime" : 25.0,
    "pct1ResTime" : 7.700000000000017,
    "pct2ResTime" : 11.949999999999989,
    "pct3ResTime" : 24.89999999999995,
    "throughput" : 10.176045588684236,
    "receivedKBytesPerSec" : 5.0383350717411215,
    "sentKBytesPerSec" : 2.255822606085275
  },
  "Login-0" : {
    "transaction" : "Login-0",
    "sampleCount" : 1,
    "errorCount" : 0,
    "errorPct" : 0.0,
    "meanResTime" : 548.0,
    "medianResTime" : 548.0,
    "minResTime" : 548.0,
    "maxResTime" : 548.0,
    "pct1ResTime" : 548.0,
    "pct2ResTime" : 548.0,
    "pct3ResTime" : 548.0,
    "throughput" : 1.8248175182481752,
    "receivedKBytesPerSec" : 1.610971715328467,
    "sentKBytesPerSec" : 1.5129590556569341
  },
  "Realizar Login 2-0" : {
    "transaction" : "Realizar Login 2-0",
    "sampleCount" : 1,
    "errorCount" : 0,
    "errorPct" : 0.0,
    "meanResTime" : 613.0,
    "medianResTime" : 613.0,
    "minResTime" : 613.0,
    "maxResTime" : 613.0,
    "pct1ResTime" : 613.0,
    "pct2ResTime" : 613.0,
    "pct3ResTime" : 613.0,
    "throughput" : 1.6313213703099512,
    "receivedKBytesPerSec" : 1.446523246329527,
    "sentKBytesPerSec" : 1.4242200244698207
  },
  "Login-1" : {
    "transaction" : "Login-1",
    "sampleCount" : 1,
    "errorCount" : 0,
    "errorPct" : 0.0,
    "meanResTime" : 672.0,
    "medianResTime" : 672.0,
    "minResTime" : 672.0,
    "maxResTime" : 672.0,
    "pct1ResTime" : 672.0,
    "pct2ResTime" : 672.0,
    "pct3ResTime" : 672.0,
    "throughput" : 1.488095238095238,
    "receivedKBytesPerSec" : 8.710588727678571,
    "sentKBytesPerSec" : 1.072474888392857
  },
  "Realizar Login 2-1" : {
    "transaction" : "Realizar Login 2-1",
    "sampleCount" : 1,
    "errorCount" : 0,
    "errorPct" : 0.0,
    "meanResTime" : 413.0,
    "medianResTime" : 413.0,
    "minResTime" : 413.0,
    "maxResTime" : 413.0,
    "pct1ResTime" : 413.0,
    "pct2ResTime" : 413.0,
    "pct3ResTime" : 413.0,
    "throughput" : 2.4213075060532687,
    "receivedKBytesPerSec" : 14.184984110169493,
    "sentKBytesPerSec" : 1.7450438861985473
  },
  "Realizar Logout" : {
    "transaction" : "Realizar Logout",
    "sampleCount" : 1,
    "errorCount" : 0,
    "errorPct" : 0.0,
    "meanResTime" : 598.0,
    "medianResTime" : 598.0,
    "minResTime" : 598.0,
    "maxResTime" : 598.0,
    "pct1ResTime" : 598.0,
    "pct2ResTime" : 598.0,
    "pct3ResTime" : 598.0,
    "throughput" : 1.6722408026755853,
    "receivedKBytesPerSec" : 6.1827184364548495,
    "sentKBytesPerSec" : 2.121328908862876
  },
  "Deletar usuário" : {
    "transaction" : "Deletar usuário",
    "sampleCount" : 1,
    "errorCount" : 0,
    "errorPct" : 0.0,
    "meanResTime" : 407.0,
    "medianResTime" : 407.0,
    "minResTime" : 407.0,
    "maxResTime" : 407.0,
    "pct1ResTime" : 407.0,
    "pct2ResTime" : 407.0,
    "pct3ResTime" : 407.0,
    "throughput" : 2.457002457002457,
    "receivedKBytesPerSec" : 6.845535165847666,
    "sentKBytesPerSec" : 1.578816031941032
  },
  "JDBC Request" : {
    "transaction" : "JDBC Request",
    "sampleCount" : 1,
    "errorCount" : 0,
    "errorPct" : 0.0,
    "meanResTime" : 802.0,
    "medianResTime" : 802.0,
    "minResTime" : 802.0,
    "maxResTime" : 802.0,
    "pct1ResTime" : 802.0,
    "pct2ResTime" : 802.0,
    "pct3ResTime" : 802.0,
    "throughput" : 1.2468827930174564,
    "receivedKBytesPerSec" : 6.325738388403989,
    "sentKBytesPerSec" : 0.0
  },
  "Consultar usuários válidos" : {
    "transaction" : "Consultar usuários válidos",
    "sampleCount" : 50,
    "errorCount" : 0,
    "errorPct" : 0.0,
    "meanResTime" : 118.78000000000002,
    "medianResTime" : 127.0,
    "minResTime" : 26.0,
    "maxResTime" : 197.0,
    "pct1ResTime" : 174.9,
    "pct2ResTime" : 183.0,
    "pct3ResTime" : 197.0,
    "throughput" : 5.129257283545343,
    "receivedKBytesPerSec" : 29.99273088069348,
    "sentKBytesPerSec" : 0.6211209991793188
  },
  "Erro de login" : {
    "transaction" : "Erro de login",
    "sampleCount" : 1279,
    "errorCount" : 1279,
    "errorPct" : 100.0,
    "meanResTime" : 150.35965598123525,
    "medianResTime" : 144.0,
    "minResTime" : 11.0,
    "maxResTime" : 282.0,
    "pct1ResTime" : 208.0,
    "pct2ResTime" : 227.0,
    "pct3ResTime" : 265.0,
    "throughput" : 48.461655046983935,
    "receivedKBytesPerSec" : 22.527097463246438,
    "sentKBytesPerSec" : 12.132064759207335
  },
  "Tela de login" : {
    "transaction" : "Tela de login",
    "sampleCount" : 1,
    "errorCount" : 0,
    "errorPct" : 0.0,
    "meanResTime" : 1340.0,
    "medianResTime" : 1340.0,
    "minResTime" : 1340.0,
    "maxResTime" : 1340.0,
    "pct1ResTime" : 1340.0,
    "pct2ResTime" : 1340.0,
    "pct3ResTime" : 1340.0,
    "throughput" : 0.746268656716418,
    "receivedKBytesPerSec" : 2.1010669309701493,
    "sentKBytesPerSec" : 0.3796933302238806
  },
  "Consultar usuários cadastrados" : {
    "transaction" : "Consultar usuários cadastrados",
    "sampleCount" : 50,
    "errorCount" : 0,
    "errorPct" : 0.0,
    "meanResTime" : 6.519999999999999,
    "medianResTime" : 5.0,
    "minResTime" : 3.0,
    "maxResTime" : 31.0,
    "pct1ResTime" : 12.0,
    "pct2ResTime" : 17.04999999999996,
    "pct3ResTime" : 31.0,
    "throughput" : 5.086987486010784,
    "receivedKBytesPerSec" : 4.413160354563027,
    "sentKBytesPerSec" : 0.6160023908841183
  },
  "Realizar Login 2" : {
    "transaction" : "Realizar Login 2",
    "sampleCount" : 1,
    "errorCount" : 0,
    "errorPct" : 0.0,
    "meanResTime" : 1026.0,
    "medianResTime" : 1026.0,
    "minResTime" : 1026.0,
    "maxResTime" : 1026.0,
    "pct1ResTime" : 1026.0,
    "pct2ResTime" : 1026.0,
    "pct3ResTime" : 1026.0,
    "throughput" : 0.9746588693957114,
    "receivedKBytesPerSec" : 6.574188291910331,
    "sentKBytesPerSec" : 1.5533625730994152
  },
  "Cadastro de usuário" : {
    "transaction" : "Cadastro de usuário",
    "sampleCount" : 50,
    "errorCount" : 0,
    "errorPct" : 0.0,
    "meanResTime" : 228.50000000000003,
    "medianResTime" : 249.0,
    "minResTime" : 32.0,
    "maxResTime" : 370.0,
    "pct1ResTime" : 350.2,
    "pct2ResTime" : 363.04999999999995,
    "pct3ResTime" : 370.0,
    "throughput" : 5.067396371744198,
    "receivedKBytesPerSec" : 2.4990577809871284,
    "sentKBytesPerSec" : 1.4959706281037801
  },
  "Login usuário com sucesso" : {
    "transaction" : "Login usuário com sucesso",
    "sampleCount" : 1279,
    "errorCount" : 0,
    "errorPct" : 0.0,
    "meanResTime" : 135.18139171227514,
    "medianResTime" : 132.0,
    "minResTime" : 18.0,
    "maxResTime" : 266.0,
    "pct1ResTime" : 185.0,
    "pct2ResTime" : 201.0,
    "pct3ResTime" : 247.60000000000014,
    "throughput" : 77.87858491140474,
    "receivedKBytesPerSec" : 53.90472774462644,
    "sentKBytesPerSec" : 19.800617845399746
  },
  "Conta cadastrada com sucesso" : {
    "transaction" : "Conta cadastrada com sucesso",
    "sampleCount" : 1,
    "errorCount" : 0,
    "errorPct" : 0.0,
    "meanResTime" : 308.0,
    "medianResTime" : 308.0,
    "minResTime" : 308.0,
    "maxResTime" : 308.0,
    "pct1ResTime" : 308.0,
    "pct2ResTime" : 308.0,
    "pct3ResTime" : 308.0,
    "throughput" : 3.246753246753247,
    "receivedKBytesPerSec" : 9.004667207792208,
    "sentKBytesPerSec" : 2.108487215909091
  },
  "Login usuário com sucesso - Teste de pico" : {
    "transaction" : "Login usuário com sucesso - Teste de pico",
    "sampleCount" : 92929,
    "errorCount" : 0,
    "errorPct" : 0.0,
    "meanResTime" : 219.98924985741465,
    "medianResTime" : 89.0,
    "minResTime" : 0.0,
    "maxResTime" : 554.0,
    "pct1ResTime" : 148.0,
    "pct2ResTime" : 164.0,
    "pct3ResTime" : 182.0,
    "throughput" : 931.787189668311,
    "receivedKBytesPerSec" : 645.3633334994034,
    "sentKBytesPerSec" : 237.22518733016986
  },
  "Criar nova conta" : {
    "transaction" : "Criar nova conta",
    "sampleCount" : 1,
    "errorCount" : 0,
    "errorPct" : 0.0,
    "meanResTime" : 398.0,
    "medianResTime" : 398.0,
    "minResTime" : 398.0,
    "maxResTime" : 398.0,
    "pct1ResTime" : 398.0,
    "pct2ResTime" : 398.0,
    "pct3ResTime" : 398.0,
    "throughput" : 2.512562814070352,
    "receivedKBytesPerSec" : 11.797267587939698,
    "sentKBytesPerSec" : 2.1346969221105527
  },
  "Login" : {
    "transaction" : "Login",
    "sampleCount" : 1,
    "errorCount" : 0,
    "errorPct" : 0.0,
    "meanResTime" : 1223.0,
    "medianResTime" : 1223.0,
    "minResTime" : 1223.0,
    "maxResTime" : 1223.0,
    "pct1ResTime" : 1223.0,
    "pct2ResTime" : 1223.0,
    "pct3ResTime" : 1223.0,
    "throughput" : 0.8176614881439085,
    "receivedKBytesPerSec" : 5.508036079313164,
    "sentKBytesPerSec" : 1.2672156071136549
  },
  "Realizar Logout-0" : {
    "transaction" : "Realizar Logout-0",
    "sampleCount" : 1,
    "errorCount" : 0,
    "errorPct" : 0.0,
    "meanResTime" : 290.0,
    "medianResTime" : 290.0,
    "minResTime" : 290.0,
    "maxResTime" : 290.0,
    "pct1ResTime" : 290.0,
    "pct2ResTime" : 290.0,
    "pct3ResTime" : 290.0,
    "throughput" : 3.4482758620689653,
    "receivedKBytesPerSec" : 3.0408135775862073,
    "sentKBytesPerSec" : 2.188846982758621
  },
  "Formulário de cadastro" : {
    "transaction" : "Formulário de cadastro",
    "sampleCount" : 1,
    "errorCount" : 0,
    "errorPct" : 0.0,
    "meanResTime" : 1126.0,
    "medianResTime" : 1126.0,
    "minResTime" : 1126.0,
    "maxResTime" : 1126.0,
    "pct1ResTime" : 1126.0,
    "pct2ResTime" : 1126.0,
    "pct3ResTime" : 1126.0,
    "throughput" : 0.8880994671403197,
    "receivedKBytesPerSec" : 3.2696630772646538,
    "sentKBytesPerSec" : 1.5879981682948492
  },
  "Realizar Logout-1" : {
    "transaction" : "Realizar Logout-1",
    "sampleCount" : 1,
    "errorCount" : 0,
    "errorPct" : 0.0,
    "meanResTime" : 306.0,
    "medianResTime" : 306.0,
    "minResTime" : 306.0,
    "maxResTime" : 306.0,
    "pct1ResTime" : 306.0,
    "pct2ResTime" : 306.0,
    "pct3ResTime" : 306.0,
    "throughput" : 3.2679738562091503,
    "receivedKBytesPerSec" : 9.200750612745098,
    "sentKBytesPerSec" : 2.071206086601307
  },
  "Debug Sampler" : {
    "transaction" : "Debug Sampler",
    "sampleCount" : 1965,
    "errorCount" : 0,
    "errorPct" : 0.0,
    "meanResTime" : 0.17353689567430072,
    "medianResTime" : 0.0,
    "minResTime" : 0.0,
    "maxResTime" : 12.0,
    "pct1ResTime" : 1.0,
    "pct2ResTime" : 1.0,
    "pct3ResTime" : 1.0,
    "throughput" : 19.62076506006051,
    "receivedKBytesPerSec" : 43.7739369901347,
    "sentKBytesPerSec" : 0.0
  },
  "Formulário de cadastro-0" : {
    "transaction" : "Formulário de cadastro-0",
    "sampleCount" : 1,
    "errorCount" : 0,
    "errorPct" : 0.0,
    "meanResTime" : 823.0,
    "medianResTime" : 823.0,
    "minResTime" : 823.0,
    "maxResTime" : 823.0,
    "pct1ResTime" : 823.0,
    "pct2ResTime" : 823.0,
    "pct3ResTime" : 823.0,
    "throughput" : 1.215066828675577,
    "receivedKBytesPerSec" : 1.0904750151883353,
    "sentKBytesPerSec" : 1.2779560297691375
  },
  "Realizar login" : {
    "transaction" : "Realizar login",
    "sampleCount" : 1,
    "errorCount" : 0,
    "errorPct" : 0.0,
    "meanResTime" : 629.0,
    "medianResTime" : 629.0,
    "minResTime" : 629.0,
    "maxResTime" : 629.0,
    "pct1ResTime" : 629.0,
    "pct2ResTime" : 629.0,
    "pct3ResTime" : 629.0,
    "throughput" : 1.589825119236884,
    "receivedKBytesPerSec" : 10.487567070747218,
    "sentKBytesPerSec" : 2.5337837837837838
  },
  "Formulário de cadastro-1" : {
    "transaction" : "Formulário de cadastro-1",
    "sampleCount" : 1,
    "errorCount" : 0,
    "errorPct" : 0.0,
    "meanResTime" : 302.0,
    "medianResTime" : 302.0,
    "minResTime" : 302.0,
    "maxResTime" : 302.0,
    "pct1ResTime" : 302.0,
    "pct2ResTime" : 302.0,
    "pct3ResTime" : 302.0,
    "throughput" : 3.3112582781456954,
    "receivedKBytesPerSec" : 9.219138038079471,
    "sentKBytesPerSec" : 2.4381725993377485
  },
  "Total" : {
    "transaction" : "Total",
    "sampleCount" : 100135,
    "errorCount" : 1329,
    "errorPct" : 1.3272083,
    "meanResTime" : 213.33765416687731,
    "medianResTime" : 88.0,
    "minResTime" : 0.0,
    "maxResTime" : 1340.0,
    "pct1ResTime" : 130.0,
    "pct2ResTime" : 151.0,
    "pct3ResTime" : 177.0,
    "throughput" : 903.5579257013436,
    "receivedKBytesPerSec" : 855.045170212298,
    "sentKBytesPerSec" : 222.55484251915217
  },
  "Capturar token" : {
    "transaction" : "Capturar token",
    "sampleCount" : 1,
    "errorCount" : 0,
    "errorPct" : 0.0,
    "meanResTime" : 1338.0,
    "medianResTime" : 1338.0,
    "minResTime" : 1338.0,
    "maxResTime" : 1338.0,
    "pct1ResTime" : 1338.0,
    "pct2ResTime" : 1338.0,
    "pct3ResTime" : 1338.0,
    "throughput" : 0.7473841554559043,
    "receivedKBytesPerSec" : 2.2020097627055306,
    "sentKBytesPerSec" : 0.3912088938714499
  },
  "Consultar usuários válidos - teste de pico" : {
    "transaction" : "Consultar usuários válidos - teste de pico",
    "sampleCount" : 2362,
    "errorCount" : 0,
    "errorPct" : 0.0,
    "meanResTime" : 218.4276037256559,
    "medianResTime" : 194.0,
    "minResTime" : 3.0,
    "maxResTime" : 553.0,
    "pct1ResTime" : 423.0,
    "pct2ResTime" : 489.0,
    "pct3ResTime" : 527.3699999999999,
    "throughput" : 23.65477251559793,
    "receivedKBytesPerSec" : 237.87608409361764,
    "sentKBytesPerSec" : 2.864445109310687
  },
  "HTTP Request" : {
    "transaction" : "HTTP Request",
    "sampleCount" : 50,
    "errorCount" : 0,
    "errorPct" : 0.0,
    "meanResTime" : 117.85999999999997,
    "medianResTime" : 124.5,
    "minResTime" : 23.0,
    "maxResTime" : 217.0,
    "pct1ResTime" : 186.0,
    "pct2ResTime" : 193.89999999999998,
    "pct3ResTime" : 217.0,
    "throughput" : 5.113520147269381,
    "receivedKBytesPerSec" : 29.965827303640825,
    "sentKBytesPerSec" : 0.6192153303334015
  }
}